sl/SLAPIClient.py
sl/__init__.py
sl/const.py
api_sl-0.0.2.dist-info/LICENSE
api_sl-0.0.2.dist-info/METADATA
api_sl-0.0.2.dist-info/WHEEL
api_sl-0.0.2.dist-info/top_level.txt
api_sl-0.0.2.dist-info/RECORD
