Metadata-Version: 2.1
Name: api-sl
Version: 0.0.2
Summary: SL API package
Home-page: https://github.com/veulsan/api-sl
Author: Ulrik Sannsell
Author-email: Ulrik Sannsell <ulrik@sannsell.se>
Project-URL: Homepage, https://github.com/veulsan/api-sl
Project-URL: Issues, https://github.com/veulsan/api-sl/issues
Classifier: Programming Language :: Python :: 3
Classifier: License :: OSI Approved :: MIT License
Classifier: Operating System :: OS Independent
Requires-Python: >=3.8
License-File: LICENSE
